pxtrade/__init__.py
pxtrade/backtest.py
pxtrade/events_queue.py
pxtrade/history.py
pxtrade/observable.py
pxtrade/settings.py
pxtrade/strategy.py
pxtrade/util.py
pxtrade/assets/__init__.py
pxtrade/assets/asset.py
pxtrade/assets/cash.py
pxtrade/assets/codes.py
pxtrade/assets/fx_rates.py
pxtrade/assets/portfolio.py
pxtrade/assets/stock.py
pxtrade/broker/__init__.py
pxtrade/broker/broker.py
pxtrade/broker/charges.py
pxtrade/broker/execution.py
pxtrade/compliance/__init__.py
pxtrade/compliance/base.py
pxtrade/compliance/position_limits.py
pxtrade/events/__init__.py
pxtrade/events/asset_price_event.py
pxtrade/events/base.py
pxtrade/events/fx_rate_event.py
pxtrade/events/indicator_event.py
pxtrade/events/load_frame_events.py
pxtrade/events/trade_event.py
pxtrade/events/yahoo.py
pxtrade/trade/__init__.py
pxtrade/trade/trade.py
pxtrade/trade/trade_pipeline.py
pxtrade-0.2.0.dist-info/LICENSE
pxtrade-0.2.0.dist-info/METADATA
pxtrade-0.2.0.dist-info/WHEEL
pxtrade-0.2.0.dist-info/top_level.txt
pxtrade-0.2.0.dist-info/RECORD
