Metadata-Version: 2.1
Name: pxtrade
Version: 0.2.0
Summary: A multi currency, event driven backtester written in Python.
Home-page: https://github.com/simongarisch/pxtrade
Author: Simon Garisch
Author-email: gatman946@gmail.com
License: UNKNOWN
Platform: UNKNOWN
Requires-Dist: pandas (>=1.1.1)
Requires-Dist: pandas-datareader (>=0.9.0)
Requires-Dist: ipython (==7.15.0)
Requires-Dist: cufflinks (>=0.17.3)
